spice_manager/__init__.py
spice_manager/constants.py
spice_manager/spicemanager.py
spice_manager-1.2.0.dist-info/LICENSE
spice_manager-1.2.0.dist-info/METADATA
spice_manager-1.2.0.dist-info/WHEEL
spice_manager-1.2.0.dist-info/RECORD
