Metadata-Version: 2.1
Name: spice_manager
Version: 1.2.0
Summary: Package to deal with Solar Orbiter SPICE kernels
Home-page: https://gitlab.obspm.fr/ROC_PUBLIC/spice_manager
License: CeCILL 2.1
Author: Xavier Bonnin
Author-email: xavier.bonnin@obspm.fr
Requires-Python: >=3.9,<4
Classifier: License :: Other/Proprietary License
Classifier: Programming Language :: Python :: 3
Classifier: Programming Language :: Python :: 3.9
Classifier: Programming Language :: Python :: 3.10
Classifier: Programming Language :: Python :: 3.11
Classifier: Programming Language :: Python :: 3.12
Classifier: Programming Language :: Python :: 3.13
Requires-Dist: spiceypy (<7)
Project-URL: Repository, https://gitlab.obspm.fr/ROC_PUBLIC/spice_manager
